{
  "ESLinting": [
    {
      "type": "ESLinting",
      "description": "All imports in the declaration are only used as types. Use `import type`.",
      "position": {
        "filePath": "/home/chico/dev/kadena-snap/packages/snap/src/index.ts",
        "lineNum": 23
      },
      "riskRating": 1
    },
    {
      "type": "ESLinting",
      "description": "Expected only 0 line after block description",
      "position": {
        "filePath": "/home/chico/dev/kadena-snap/packages/snap/src/index.ts",
        "lineNum": 33
      },
      "riskRating": 1
    },
    {
      "type": "ESLinting",
      "description": "Expected an error object to be thrown.",
      "position": {
        "filePath": "/home/chico/dev/kadena-snap/packages/snap/src/index.ts",
        "lineNum": 130
      },
      "riskRating": 1
    },
    {
      "type": "ESLinting",
      "description": "All imports in the declaration are only used as types. Use `import type`.",
      "position": {
        "filePath": "/home/chico/dev/kadena-snap/packages/snap/src/services/addAccount.ts",
        "lineNum": 1
      },
      "riskRating": 1
    },
    {
      "type": "ESLinting",
      "description": "Missing JSDoc @param \"snapApi\" declaration.",
      "position": {
        "filePath": "/home/chico/dev/kadena-snap/packages/snap/src/services/addAccount.ts",
        "lineNum": 12
      },
      "riskRating": 1
    },
    {
      "type": "ESLinting",
      "description": "Expected @param names to be \"snapApi\". Got \"requestParams\".",
      "position": {
        "filePath": "/home/chico/dev/kadena-snap/packages/snap/src/services/addAccount.ts",
        "lineNum": 14
      },
      "riskRating": 1
    },
    {
      "type": "ESLinting",
      "description": "Missing JSDoc @param \"requestParams\" description.",
      "position": {
        "filePath": "/home/chico/dev/kadena-snap/packages/snap/src/services/addAccount.ts",
        "lineNum": 14
      },
      "riskRating": 1
    },
    {
      "type": "ESLinting",
      "description": "'getNextIndex' was used before it was defined.",
      "position": {
        "filePath": "/home/chico/dev/kadena-snap/packages/snap/src/services/addAccount.ts",
        "lineNum": 18
      },
      "riskRating": 1
    },
    {
      "type": "ESLinting",
      "description": "Missing JSDoc comment.",
      "position": {
        "filePath": "/home/chico/dev/kadena-snap/packages/snap/src/services/addAccount.ts",
        "lineNum": 35
      },
      "riskRating": 1
    },
    {
      "type": "ESLinting",
      "description": "Missing JSDoc comment.",
      "position": {
        "filePath": "/home/chico/dev/kadena-snap/packages/snap/src/services/addAccount.ts",
        "lineNum": 47
      },
      "riskRating": 1
    },
    {
      "type": "ESLinting",
      "description": "Missing return type on function.",
      "position": {
        "filePath": "/home/chico/dev/kadena-snap/packages/snap/src/services/addAccount.ts",
        "lineNum": 66
      },
      "riskRating": 1
    },
    {
      "type": "ESLinting",
      "description": "All imports in the declaration are only used as types. Use `import type`.",
      "position": {
        "filePath": "/home/chico/dev/kadena-snap/packages/snap/src/services/deleteAccount.ts",
        "lineNum": 6
      },
      "riskRating": 1
    },
    {
      "type": "ESLinting",
      "description": "Missing return type on function.",
      "position": {
        "filePath": "/home/chico/dev/kadena-snap/packages/snap/src/services/deleteAccount.ts",
        "lineNum": 17
      },
      "riskRating": 1
    },
    {
      "type": "ESLinting",
      "description": "Expected an error object to be thrown.",
      "position": {
        "filePath": "/home/chico/dev/kadena-snap/packages/snap/src/services/deleteAccount.ts",
        "lineNum": 29
      },
      "riskRating": 1
    },
    {
      "type": "ESLinting",
      "description": "Expected an error object to be thrown.",
      "position": {
        "filePath": "/home/chico/dev/kadena-snap/packages/snap/src/services/deleteAccount.ts",
        "lineNum": 51
      },
      "riskRating": 1
    },
    {
      "type": "ESLinting",
      "description": "All imports in the declaration are only used as types. Use `import type`.",
      "position": {
        "filePath": "/home/chico/dev/kadena-snap/packages/snap/src/services/deleteNetwork.ts",
        "lineNum": 7
      },
      "riskRating": 1
    },
    {
      "type": "ESLinting",
      "description": "Expected an error object to be thrown.",
      "position": {
        "filePath": "/home/chico/dev/kadena-snap/packages/snap/src/services/deleteNetwork.ts",
        "lineNum": 22
      },
      "riskRating": 1
    },
    {
      "type": "ESLinting",
      "description": "'network' is already declared in the upper scope on line 25 column 9.",
      "position": {
        "filePath": "/home/chico/dev/kadena-snap/packages/snap/src/services/deleteNetwork.ts",
        "lineNum": 25
      },
      "riskRating": 1
    },
    {
      "type": "ESLinting",
      "description": "Expected an error object to be thrown.",
      "position": {
        "filePath": "/home/chico/dev/kadena-snap/packages/snap/src/services/deleteNetwork.ts",
        "lineNum": 28
      },
      "riskRating": 1
    },
    {
      "type": "ESLinting",
      "description": "Expected an error object to be thrown.",
      "position": {
        "filePath": "/home/chico/dev/kadena-snap/packages/snap/src/services/deleteNetwork.ts",
        "lineNum": 32
      },
      "riskRating": 1
    },
    {
      "type": "ESLinting",
      "description": "Expected an error object to be thrown.",
      "position": {
        "filePath": "/home/chico/dev/kadena-snap/packages/snap/src/services/deleteNetwork.ts",
        "lineNum": 51
      },
      "riskRating": 1
    },
    {
      "type": "ESLinting",
      "description": "'network' is already declared in the upper scope on line 25 column 9.",
      "position": {
        "filePath": "/home/chico/dev/kadena-snap/packages/snap/src/services/deleteNetwork.ts",
        "lineNum": 55
      },
      "riskRating": 1
    },
    {
      "type": "ESLinting",
      "description": "All imports in the declaration are only used as types. Use `import type`.",
      "position": {
        "filePath": "/home/chico/dev/kadena-snap/packages/snap/src/services/getAccounts_v2.ts",
        "lineNum": 1
      },
      "riskRating": 1
    },
    {
      "type": "ESLinting",
      "description": "Variable name `getAccounts_v2` must match one of the following formats: camelCase, UPPER_CASE, PascalCase",
      "position": {
        "filePath": "/home/chico/dev/kadena-snap/packages/snap/src/services/getAccounts_v2.ts",
        "lineNum": 6
      },
      "riskRating": 1
    },
    {
      "type": "ESLinting",
      "description": "All imports in the declaration are only used as types. Use `import type`.",
      "position": {
        "filePath": "/home/chico/dev/kadena-snap/packages/snap/src/services/getAccounts.ts",
        "lineNum": 1
      },
      "riskRating": 1
    },
    {
      "type": "ESLinting",
      "description": "Missing return type on function.",
      "position": {
        "filePath": "/home/chico/dev/kadena-snap/packages/snap/src/services/getAccounts.ts",
        "lineNum": 3
      },
      "riskRating": 1
    },
    {
      "type": "ESLinting",
      "description": "Missing return type on function.",
      "position": {
        "filePath": "/home/chico/dev/kadena-snap/packages/snap/src/services/getAccounts.ts",
        "lineNum": 7
      },
      "riskRating": 1
    },
    {
      "type": "ESLinting",
      "description": "All imports in the declaration are only used as types. Use `import type`.",
      "position": {
        "filePath": "/home/chico/dev/kadena-snap/packages/snap/src/services/getActiveNetwork.ts",
        "lineNum": 1
      },
      "riskRating": 1
    },
    {
      "type": "ESLinting",
      "description": "All imports in the declaration are only used as types. Use `import type`.",
      "position": {
        "filePath": "/home/chico/dev/kadena-snap/packages/snap/src/services/getNetwork_v1.ts",
        "lineNum": 1
      },
      "riskRating": 1
    },
    {
      "type": "ESLinting",
      "description": "Variable name `getNetwork_v1` must match one of the following formats: camelCase, UPPER_CASE, PascalCase",
      "position": {
        "filePath": "/home/chico/dev/kadena-snap/packages/snap/src/services/getNetwork_v1.ts",
        "lineNum": 5
      },
      "riskRating": 1
    },
    {
      "type": "ESLinting",
      "description": "All imports in the declaration are only used as types. Use `import type`.",
      "position": {
        "filePath": "/home/chico/dev/kadena-snap/packages/snap/src/services/getNetworks_v1.ts",
        "lineNum": 1
      },
      "riskRating": 1
    },
    {
      "type": "ESLinting",
      "description": "Variable name `getNetworks_v1` must match one of the following formats: camelCase, UPPER_CASE, PascalCase",
      "position": {
        "filePath": "/home/chico/dev/kadena-snap/packages/snap/src/services/getNetworks_v1.ts",
        "lineNum": 5
      },
      "riskRating": 1
    },
    {
      "type": "ESLinting",
      "description": "All imports in the declaration are only used as types. Use `import type`.",
      "position": {
        "filePath": "/home/chico/dev/kadena-snap/packages/snap/src/services/getNetworks.ts",
        "lineNum": 1
      },
      "riskRating": 1
    },
    {
      "type": "ESLinting",
      "description": "All imports in the declaration are only used as types. Use `import type`.",
      "position": {
        "filePath": "/home/chico/dev/kadena-snap/packages/snap/src/services/setAccountName.ts",
        "lineNum": 3
      },
      "riskRating": 1
    },
    {
      "type": "ESLinting",
      "description": "'account' is already declared in the upper scope on line 24 column 9.",
      "position": {
        "filePath": "/home/chico/dev/kadena-snap/packages/snap/src/services/setAccountName.ts",
        "lineNum": 24
      },
      "riskRating": 1
    },
    {
      "type": "ESLinting",
      "description": "Expected an error object to be thrown.",
      "position": {
        "filePath": "/home/chico/dev/kadena-snap/packages/snap/src/services/setAccountName.ts",
        "lineNum": 26
      },
      "riskRating": 1
    },
    {
      "type": "ESLinting",
      "description": "'account' is already declared in the upper scope on line 24 column 9.",
      "position": {
        "filePath": "/home/chico/dev/kadena-snap/packages/snap/src/services/setAccountName.ts",
        "lineNum": 29
      },
      "riskRating": 1
    },
    {
      "type": "ESLinting",
      "description": "All imports in the declaration are only used as types. Use `import type`.",
      "position": {
        "filePath": "/home/chico/dev/kadena-snap/packages/snap/src/services/setActiveNetwork.ts",
        "lineNum": 7
      },
      "riskRating": 1
    },
    {
      "type": "ESLinting",
      "description": "'network' is already declared in the upper scope on line 22 column 9.",
      "position": {
        "filePath": "/home/chico/dev/kadena-snap/packages/snap/src/services/setActiveNetwork.ts",
        "lineNum": 22
      },
      "riskRating": 1
    },
    {
      "type": "ESLinting",
      "description": "Expected an error object to be thrown.",
      "position": {
        "filePath": "/home/chico/dev/kadena-snap/packages/snap/src/services/setActiveNetwork.ts",
        "lineNum": 25
      },
      "riskRating": 1
    },
    {
      "type": "ESLinting",
      "description": "Expected an error object to be thrown.",
      "position": {
        "filePath": "/home/chico/dev/kadena-snap/packages/snap/src/services/setActiveNetwork.ts",
        "lineNum": 42
      },
      "riskRating": 1
    },
    {
      "type": "ESLinting",
      "description": "All imports in the declaration are only used as types. Use `import type`.",
      "position": {
        "filePath": "/home/chico/dev/kadena-snap/packages/snap/src/services/signTransaction.ts",
        "lineNum": 11
      },
      "riskRating": 1
    },
    {
      "type": "ESLinting",
      "description": "All imports in the declaration are only used as types. Use `import type`.",
      "position": {
        "filePath": "/home/chico/dev/kadena-snap/packages/snap/src/services/signTransaction.ts",
        "lineNum": 12
      },
      "riskRating": 1
    },
    {
      "type": "ESLinting",
      "description": "Missing JSDoc comment.",
      "position": {
        "filePath": "/home/chico/dev/kadena-snap/packages/snap/src/services/signTransaction.ts",
        "lineNum": 21
      },
      "riskRating": 1
    },
    {
      "type": "ESLinting",
      "description": "Missing JSDoc @param \"snapApi\" declaration.",
      "position": {
        "filePath": "/home/chico/dev/kadena-snap/packages/snap/src/services/signTransaction.ts",
        "lineNum": 28
      },
      "riskRating": 1
    },
    {
      "type": "ESLinting",
      "description": "'account' is already declared in the upper scope on line 40 column 9.",
      "position": {
        "filePath": "/home/chico/dev/kadena-snap/packages/snap/src/services/signTransaction.ts",
        "lineNum": 40
      },
      "riskRating": 1
    },
    {
      "type": "ESLinting",
      "description": "Expected an error object to be thrown.",
      "position": {
        "filePath": "/home/chico/dev/kadena-snap/packages/snap/src/services/signTransaction.ts",
        "lineNum": 42
      },
      "riskRating": 1
    },
    {
      "type": "ESLinting",
      "description": "Expected an error object to be thrown.",
      "position": {
        "filePath": "/home/chico/dev/kadena-snap/packages/snap/src/services/signTransaction.ts",
        "lineNum": 48
      },
      "riskRating": 1
    },
    {
      "type": "ESLinting",
      "description": "'e' is defined but never used.",
      "position": {
        "filePath": "/home/chico/dev/kadena-snap/packages/snap/src/services/signTransaction.ts",
        "lineNum": 54
      },
      "riskRating": 1
    },
    {
      "type": "ESLinting",
      "description": "Expected an error object to be thrown.",
      "position": {
        "filePath": "/home/chico/dev/kadena-snap/packages/snap/src/services/signTransaction.ts",
        "lineNum": 55
      },
      "riskRating": 1
    },
    {
      "type": "ESLinting",
      "description": "Expected an error object to be thrown.",
      "position": {
        "filePath": "/home/chico/dev/kadena-snap/packages/snap/src/services/signTransaction.ts",
        "lineNum": 65
      },
      "riskRating": 1
    },
    {
      "type": "ESLinting",
      "description": "Expected an error object to be thrown.",
      "position": {
        "filePath": "/home/chico/dev/kadena-snap/packages/snap/src/services/signTransaction.ts",
        "lineNum": 69
      },
      "riskRating": 1
    },
    {
      "type": "ESLinting",
      "description": "Expected an error object to be thrown.",
      "position": {
        "filePath": "/home/chico/dev/kadena-snap/packages/snap/src/services/signTransaction.ts",
        "lineNum": 78
      },
      "riskRating": 1
    },
    {
      "type": "ESLinting",
      "description": "Expected an error object to be thrown.",
      "position": {
        "filePath": "/home/chico/dev/kadena-snap/packages/snap/src/services/signTransaction.ts",
        "lineNum": 84
      },
      "riskRating": 1
    },
    {
      "type": "ESLinting",
      "description": "Expected an error object to be thrown.",
      "position": {
        "filePath": "/home/chico/dev/kadena-snap/packages/snap/src/services/signTransaction.ts",
        "lineNum": 98
      },
      "riskRating": 1
    },
    {
      "type": "ESLinting",
      "description": "Expected an error object to be thrown.",
      "position": {
        "filePath": "/home/chico/dev/kadena-snap/packages/snap/src/services/signTransaction.ts",
        "lineNum": 102
      },
      "riskRating": 1
    },
    {
      "type": "ESLinting",
      "description": "Expected an error object to be thrown.",
      "position": {
        "filePath": "/home/chico/dev/kadena-snap/packages/snap/src/services/signTransaction.ts",
        "lineNum": 111
      },
      "riskRating": 1
    },
    {
      "type": "ESLinting",
      "description": "Missing JSDoc comment.",
      "position": {
        "filePath": "/home/chico/dev/kadena-snap/packages/snap/src/services/signTransaction.ts",
        "lineNum": 126
      },
      "riskRating": 1
    },
    {
      "type": "ESLinting",
      "description": "Missing return type on function.",
      "position": {
        "filePath": "/home/chico/dev/kadena-snap/packages/snap/src/services/signTransaction.ts",
        "lineNum": 126
      },
      "riskRating": 1
    },
    {
      "type": "ESLinting",
      "description": "Missing JSDoc comment.",
      "position": {
        "filePath": "/home/chico/dev/kadena-snap/packages/snap/src/services/signTransaction.ts",
        "lineNum": 148
      },
      "riskRating": 1
    },
    {
      "type": "ESLinting",
      "description": "Missing return type on function.",
      "position": {
        "filePath": "/home/chico/dev/kadena-snap/packages/snap/src/services/signTransaction.ts",
        "lineNum": 148
      },
      "riskRating": 1
    },
    {
      "type": "ESLinting",
      "description": "All imports in the declaration are only used as types. Use `import type`.",
      "position": {
        "filePath": "/home/chico/dev/kadena-snap/packages/snap/src/services/storeAccount.ts",
        "lineNum": 2
      },
      "riskRating": 1
    },
    {
      "type": "ESLinting",
      "description": "All imports in the declaration are only used as types. Use `import type`.",
      "position": {
        "filePath": "/home/chico/dev/kadena-snap/packages/snap/src/services/storeNetwork.ts",
        "lineNum": 7
      },
      "riskRating": 1
    },
    {
      "type": "ESLinting",
      "description": "Expected an error object to be thrown.",
      "position": {
        "filePath": "/home/chico/dev/kadena-snap/packages/snap/src/services/storeNetwork.ts",
        "lineNum": 41
      },
      "riskRating": 1
    },
    {
      "type": "ESLinting",
      "description": "Expected an error object to be thrown.",
      "position": {
        "filePath": "/home/chico/dev/kadena-snap/packages/snap/src/services/storeNetwork.ts",
        "lineNum": 65
      },
      "riskRating": 1
    },
    {
      "type": "ESLinting",
      "description": "All exports in the declaration are only used as types. Use `export type`.",
      "position": {
        "filePath": "/home/chico/dev/kadena-snap/packages/snap/src/types/index.ts",
        "lineNum": 1
      },
      "riskRating": 1
    },
    {
      "type": "ESLinting",
      "description": "All exports in the declaration are only used as types. Use `export type`.",
      "position": {
        "filePath": "/home/chico/dev/kadena-snap/packages/snap/src/types/index.ts",
        "lineNum": 2
      },
      "riskRating": 1
    },
    {
      "type": "ESLinting",
      "description": "All exports in the declaration are only used as types. Use `export type`.",
      "position": {
        "filePath": "/home/chico/dev/kadena-snap/packages/snap/src/types/index.ts",
        "lineNum": 3
      },
      "riskRating": 1
    },
    {
      "type": "ESLinting",
      "description": "All imports in the declaration are only used as types. Use `import type`.",
      "position": {
        "filePath": "/home/chico/dev/kadena-snap/packages/snap/src/types/snapApi.ts",
        "lineNum": 1
      },
      "riskRating": 1
    },
    {
      "type": "ESLinting",
      "description": "All imports in the declaration are only used as types. Use `import type`.",
      "position": {
        "filePath": "/home/chico/dev/kadena-snap/packages/snap/src/types/snapApi.ts",
        "lineNum": 2
      },
      "riskRating": 1
    },
    {
      "type": "ESLinting",
      "description": "Use a `type` instead of an `interface`.",
      "position": {
        "filePath": "/home/chico/dev/kadena-snap/packages/snap/src/types/snapApi.ts",
        "lineNum": 4
      },
      "riskRating": 1
    },
    {
      "type": "ESLinting",
      "description": "Missing JSDoc comment.",
      "position": {
        "filePath": "/home/chico/dev/kadena-snap/packages/snap/src/utils/createDefaultNetworks.ts",
        "lineNum": 4
      },
      "riskRating": 1
    },
    {
      "type": "ESLinting",
      "description": "All imports in the declaration are only used as types. Use `import type`.",
      "position": {
        "filePath": "/home/chico/dev/kadena-snap/packages/snap/src/utils/kadenaUtils.ts",
        "lineNum": 2
      },
      "riskRating": 1
    },
    {
      "type": "ESLinting",
      "description": "Missing JSDoc comment.",
      "position": {
        "filePath": "/home/chico/dev/kadena-snap/packages/snap/src/utils/kadenaUtils.ts",
        "lineNum": 5
      },
      "riskRating": 1
    },
    {
      "type": "ESLinting",
      "description": "Missing return type on function.",
      "position": {
        "filePath": "/home/chico/dev/kadena-snap/packages/snap/src/utils/kadenaUtils.ts",
        "lineNum": 5
      },
      "riskRating": 1
    },
    {
      "type": "ESLinting",
      "description": "Use a `type` instead of an `interface`.",
      "position": {
        "filePath": "/home/chico/dev/kadena-snap/packages/snap/src/utils/kadenaUtils.ts",
        "lineNum": 18
      },
      "riskRating": 1
    },
    {
      "type": "ESLinting",
      "description": "Use a `type` instead of an `interface`.",
      "position": {
        "filePath": "/home/chico/dev/kadena-snap/packages/snap/src/utils/parseCapabilities.ts",
        "lineNum": 4
      },
      "riskRating": 1
    },
    {
      "type": "ESLinting",
      "description": "Type Parameter name `T` must match the RegExp: /^.{3,}/u",
      "position": {
        "filePath": "/home/chico/dev/kadena-snap/packages/snap/src/utils/parseCapabilities.ts",
        "lineNum": 14
      },
      "riskRating": 1
    },
    {
      "type": "ESLinting",
      "description": "'arg' may use Object's default stringification format ('[object Object]') when stringified.",
      "position": {
        "filePath": "/home/chico/dev/kadena-snap/packages/snap/src/utils/parseCapabilities.ts",
        "lineNum": 37
      },
      "riskRating": 1
    },
    {
      "type": "ESLinting",
      "description": "Expected an error object to be thrown.",
      "position": {
        "filePath": "/home/chico/dev/kadena-snap/packages/snap/src/utils/parseCapabilities.ts",
        "lineNum": 42
      },
      "riskRating": 1
    },
    {
      "type": "ESLinting",
      "description": "Invalid type \"never\" of template literal expression.",
      "position": {
        "filePath": "/home/chico/dev/kadena-snap/packages/snap/src/utils/parseCapabilities.ts",
        "lineNum": 42
      },
      "riskRating": 1
    },
    {
      "type": "ESLinting",
      "description": "'sender' may use Object's default stringification format ('[object Object]') when stringified.",
      "position": {
        "filePath": "/home/chico/dev/kadena-snap/packages/snap/src/utils/parseCapabilities.ts",
        "lineNum": 46
      },
      "riskRating": 1
    },
    {
      "type": "ESLinting",
      "description": "Invalid type \"PactValue\" of template literal expression.",
      "position": {
        "filePath": "/home/chico/dev/kadena-snap/packages/snap/src/utils/parseCapabilities.ts",
        "lineNum": 46
      },
      "riskRating": 1
    },
    {
      "type": "ESLinting",
      "description": "'receiver' may use Object's default stringification format ('[object Object]') when stringified.",
      "position": {
        "filePath": "/home/chico/dev/kadena-snap/packages/snap/src/utils/parseCapabilities.ts",
        "lineNum": 46
      },
      "riskRating": 1
    },
    {
      "type": "ESLinting",
      "description": "Invalid type \"PactValue\" of template literal expression.",
      "position": {
        "filePath": "/home/chico/dev/kadena-snap/packages/snap/src/utils/parseCapabilities.ts",
        "lineNum": 46
      },
      "riskRating": 1
    },
    {
      "type": "ESLinting",
      "description": "'destinationChainId' may use Object's default stringification format ('[object Object]') when stringified.",
      "position": {
        "filePath": "/home/chico/dev/kadena-snap/packages/snap/src/utils/parseCapabilities.ts",
        "lineNum": 46
      },
      "riskRating": 1
    },
    {
      "type": "ESLinting",
      "description": "Invalid type \"PactValue\" of template literal expression.",
      "position": {
        "filePath": "/home/chico/dev/kadena-snap/packages/snap/src/utils/parseCapabilities.ts",
        "lineNum": 46
      },
      "riskRating": 1
    },
    {
      "type": "ESLinting",
      "description": "Expected an error object to be thrown.",
      "position": {
        "filePath": "/home/chico/dev/kadena-snap/packages/snap/src/utils/parseCapabilities.ts",
        "lineNum": 49
      },
      "riskRating": 1
    },
    {
      "type": "ESLinting",
      "description": "Invalid type \"never\" of template literal expression.",
      "position": {
        "filePath": "/home/chico/dev/kadena-snap/packages/snap/src/utils/parseCapabilities.ts",
        "lineNum": 49
      },
      "riskRating": 1
    },
    {
      "type": "ESLinting",
      "description": "'sender' may use Object's default stringification format ('[object Object]') when stringified.",
      "position": {
        "filePath": "/home/chico/dev/kadena-snap/packages/snap/src/utils/parseCapabilities.ts",
        "lineNum": 53
      },
      "riskRating": 1
    },
    {
      "type": "ESLinting",
      "description": "Invalid type \"PactValue\" of template literal expression.",
      "position": {
        "filePath": "/home/chico/dev/kadena-snap/packages/snap/src/utils/parseCapabilities.ts",
        "lineNum": 53
      },
      "riskRating": 1
    },
    {
      "type": "ESLinting",
      "description": "'receiver' may use Object's default stringification format ('[object Object]') when stringified.",
      "position": {
        "filePath": "/home/chico/dev/kadena-snap/packages/snap/src/utils/parseCapabilities.ts",
        "lineNum": 53
      },
      "riskRating": 1
    },
    {
      "type": "ESLinting",
      "description": "Invalid type \"PactValue\" of template literal expression.",
      "position": {
        "filePath": "/home/chico/dev/kadena-snap/packages/snap/src/utils/parseCapabilities.ts",
        "lineNum": 53
      },
      "riskRating": 1
    },
    {
      "type": "ESLinting",
      "description": "Object Literal Method name `_unknown` must match one of the following formats: camelCase, PascalCase, UPPER_CASE",
      "position": {
        "filePath": "/home/chico/dev/kadena-snap/packages/snap/src/utils/parseCapabilities.ts",
        "lineNum": 56
      },
      "riskRating": 1
    },
    {
      "type": "ESLinting",
      "description": "Missing JSDoc comment.",
      "position": {
        "filePath": "/home/chico/dev/kadena-snap/packages/snap/src/utils/renderNetwork.ts",
        "lineNum": 4
      },
      "riskRating": 1
    },
    {
      "type": "ESLinting",
      "description": "Missing return type on function.",
      "position": {
        "filePath": "/home/chico/dev/kadena-snap/packages/snap/src/utils/renderNetwork.ts",
        "lineNum": 4
      },
      "riskRating": 1
    },
    {
      "type": "ESLinting",
      "description": "All imports in the declaration are only used as types. Use `import type`.",
      "position": {
        "filePath": "/home/chico/dev/kadena-snap/packages/snap/src/utils/renderSignatureRequest.ts",
        "lineNum": 4
      },
      "riskRating": 1
    },
    {
      "type": "ESLinting",
      "description": "Missing JSDoc comment.",
      "position": {
        "filePath": "/home/chico/dev/kadena-snap/packages/snap/src/utils/renderSignatureRequest.ts",
        "lineNum": 8
      },
      "riskRating": 1
    },
    {
      "type": "ESLinting",
      "description": "Array type using 'Array<T>' is forbidden. Use 'T[]' instead.",
      "position": {
        "filePath": "/home/chico/dev/kadena-snap/packages/snap/src/utils/renderSignatureRequest.ts",
        "lineNum": 8
      },
      "riskRating": 1
    },
    {
      "type": "ESLinting",
      "description": "Missing JSDoc comment.",
      "position": {
        "filePath": "/home/chico/dev/kadena-snap/packages/snap/src/utils/renderSignatureRequest.ts",
        "lineNum": 39
      },
      "riskRating": 1
    },
    {
      "type": "ESLinting",
      "description": "Missing return type on function.",
      "position": {
        "filePath": "/home/chico/dev/kadena-snap/packages/snap/src/utils/renderSignatureRequest.ts",
        "lineNum": 39
      },
      "riskRating": 1
    },
    {
      "type": "ESLinting",
      "description": "Unnecessary assertion: Array#reduce accepts a type parameter for the default value.",
      "position": {
        "filePath": "/home/chico/dev/kadena-snap/packages/snap/src/utils/renderSignatureRequest.ts",
        "lineNum": 43
      },
      "riskRating": 1
    },
    {
      "type": "ESLinting",
      "description": "Use a `type` instead of an `interface`.",
      "position": {
        "filePath": "/home/chico/dev/kadena-snap/packages/snap/src/utils/validate.ts",
        "lineNum": 5
      },
      "riskRating": 1
    },
    {
      "type": "ESLinting",
      "description": "Missing JSDoc comment.",
      "position": {
        "filePath": "/home/chico/dev/kadena-snap/packages/snap/src/utils/validate.ts",
        "lineNum": 11
      },
      "riskRating": 1
    },
    {
      "type": "ESLinting",
      "description": "Type Parameter name `T` must match the RegExp: /^.{3,}/u",
      "position": {
        "filePath": "/home/chico/dev/kadena-snap/packages/snap/src/utils/validate.ts",
        "lineNum": 11
      },
      "riskRating": 1
    },
    {
      "type": "ESLinting",
      "description": "Missing JSDoc comment.",
      "position": {
        "filePath": "/home/chico/dev/kadena-snap/packages/snap/src/utils/validate.ts",
        "lineNum": 15
      },
      "riskRating": 1
    },
    {
      "type": "ESLinting",
      "description": "Type Parameter name `T` must match the RegExp: /^.{3,}/u",
      "position": {
        "filePath": "/home/chico/dev/kadena-snap/packages/snap/src/utils/validate.ts",
        "lineNum": 15
      },
      "riskRating": 1
    },
    {
      "type": "ESLinting",
      "description": "Expected an error object to be thrown.",
      "position": {
        "filePath": "/home/chico/dev/kadena-snap/packages/snap/src/utils/validate.ts",
        "lineNum": 32
      },
      "riskRating": 1
    },
    {
      "type": "ESLinting",
      "description": "Missing JSDoc comment.",
      "position": {
        "filePath": "/home/chico/dev/kadena-snap/packages/snap/src/utils/validate.ts",
        "lineNum": 36
      },
      "riskRating": 1
    },
    {
      "type": "ESLinting",
      "description": "Missing return type on function.",
      "position": {
        "filePath": "/home/chico/dev/kadena-snap/packages/snap/src/utils/validate.ts",
        "lineNum": 36
      },
      "riskRating": 1
    },
    {
      "type": "ESLinting",
      "description": "Expected an error object to be thrown.",
      "position": {
        "filePath": "/home/chico/dev/kadena-snap/packages/snap/src/utils/validate.ts",
        "lineNum": 47
      },
      "riskRating": 1
    },
    {
      "type": "ESLinting",
      "description": "Invalid type \"never\" of template literal expression.",
      "position": {
        "filePath": "/home/chico/dev/kadena-snap/packages/snap/src/utils/validate.ts",
        "lineNum": 47
      },
      "riskRating": 1
    },
    {
      "type": "ESLinting",
      "description": "Missing JSDoc comment.",
      "position": {
        "filePath": "/home/chico/dev/kadena-snap/packages/snap/src/utils/validate.ts",
        "lineNum": 51
      },
      "riskRating": 1
    },
    {
      "type": "ESLinting",
      "description": "Missing JSDoc comment.",
      "position": {
        "filePath": "/home/chico/dev/kadena-snap/packages/snap/src/utils/validate.ts",
        "lineNum": 55
      },
      "riskRating": 1
    },
    {
      "type": "ESLinting",
      "description": "Missing JSDoc comment.",
      "position": {
        "filePath": "/home/chico/dev/kadena-snap/packages/snap/src/utils/validate.ts",
        "lineNum": 59
      },
      "riskRating": 1
    },
    {
      "type": "ESLinting",
      "description": "Missing JSDoc comment.",
      "position": {
        "filePath": "/home/chico/dev/kadena-snap/packages/snap/src/utils/validate.ts",
        "lineNum": 63
      },
      "riskRating": 1
    }
  ],
  "ImproperTypeUsage": [
    {
      "type": "ImproperTypeUsage",
      "description": "Parameter 'txn' in function 'transactionConfirmationDialog' uses 'any' type, which reduces type safety.",
      "position": {
        "filePath": "/home/chico/dev/kadena-snap/packages/snap/src/services/signTransaction.ts",
        "lineNum": 3455
      },
      "riskRating": 2
    },
    {
      "type": "ImproperTypeUsage",
      "description": "Parameter 'cont' in function 'continuationConfirmationDialog' uses 'any' type, which reduces type safety.",
      "position": {
        "filePath": "/home/chico/dev/kadena-snap/packages/snap/src/services/signTransaction.ts",
        "lineNum": 3886
      },
      "riskRating": 2
    },
    {
      "type": "ImproperTypeUsage",
      "description": "Parameter 'meta' in function 'continuationConfirmationDialog' uses 'any' type, which reduces type safety.",
      "position": {
        "filePath": "/home/chico/dev/kadena-snap/packages/snap/src/services/signTransaction.ts",
        "lineNum": 3897
      },
      "riskRating": 2
    }
  ],
  "UsedBeforeDefinedArrowFunctions": [
    {
      "type": "UsedBeforeDefinedArrowFunctions",
      "description": "Arrow function 'getNextIndex' is used before it is defined.",
      "position": {
        "filePath": "/home/chico/dev/kadena-snap/packages/snap/src/services/addAccount.ts",
        "lineNum": 18
      },
      "riskRating": 2
    }
  ]
}